cwms/__init__.py
cwms/bm25.py
cwms/cache.py
cwms/chunker.py
cwms/cli.py
cwms/config.py
cwms/constants.py
cwms/embedding_cache.py
cwms/embeddings.py
cwms/exceptions.py
cwms/hierarchical_summarizer.py
cwms/logging_config.py
cwms/metrics.py
cwms/model_config.py
cwms/retriever.py
cwms/retry.py
cwms/skill.py
cwms/skill_files/AUTO_SWAP_README.md
cwms/skill_files/CONTINUATION.md
cwms/skill_files/SKILL.md
cwms/skill_files/__init__.py
cwms/skill_files/config.yaml
cwms/skill_files/hooks/__init__.py
cwms/skill_files/hooks/auto-swap.py
cwms/skill_files/hooks/proactive-retrieval.py
cwms/skill_files/hooks/session-start.py
cwms/skill_files/statusline.py
cwms/storage.py
cwms/storage_adapters.py
cwms/summarizer.py
cwms/swapper.py
cwms/tokens.py
cwms/utils/__init__.py
cwms/utils/text.py
cwms/validation.py
cwms/vector_store.py
cwms-1.20.1.dist-info/METADATA
cwms-1.20.1.dist-info/WHEEL
cwms-1.20.1.dist-info/entry_points.txt
cwms-1.20.1.dist-info/licenses/LICENSE
cwms-1.20.1.dist-info/RECORD
