Metadata-Version: 2.4
Name: cwms
Version: 1.20.1
Summary: Claude Code skill for extended context through swap-to-disk memory management
License: MIT
License-File: LICENSE
Keywords: agentic,context,memory,claude,llm,swap,rag
Author: Dennis Lattka
Requires-Python: >=3.12,<3.14
Classifier: Development Status :: 3 - Alpha
Classifier: Intended Audience :: Developers
Classifier: License :: OSI Approved :: MIT License
Classifier: Operating System :: OS Independent
Classifier: Programming Language :: Python :: 3
Classifier: Programming Language :: Python :: 3.12
Classifier: Programming Language :: Python :: 3.13
Classifier: Topic :: Software Development :: Libraries :: Python Modules
Provides-Extra: all
Provides-Extra: api
Provides-Extra: local
Provides-Extra: numpy
Provides-Extra: tiktoken
Requires-Dist: anthropic (>=0.18.0) ; extra == "api" or extra == "all"
Requires-Dist: chromadb (>=1.4.1,<2.0.0)
Requires-Dist: click (>=8.1)
Requires-Dist: numpy (>=1.24.0) ; extra == "numpy" or extra == "all"
Requires-Dist: pyyaml (>=6.0)
Requires-Dist: sentence-transformers (>=2.2.0) ; extra == "local" or extra == "all"
Requires-Dist: tiktoken (>=0.8.0) ; extra == "tiktoken" or extra == "all"
Requires-Dist: torch (>=2.0.0) ; extra == "local" or extra == "all"
Project-URL: Homepage, https://github.com/Taderich73/cwms
Project-URL: Repository, https://github.com/Taderich73/cwms
